{
  "resourceType": "StructureDefinition",
  "id": "vital-status",
  "url": "https://rarelink.bih-charite.de/fhir/StructureDefinition/vital-status",
  "name": "VitalStatus",
  "title": "Vital Status",
  "status": "draft",
  "description": "Coded representation of a patient's vital status",
  "fhirVersion": "4.0.1",
  "kind": "complex-type",
  "abstract": false,
  "context": [
    {
      "type": "element",
      "expression": "Element"
    }
  ],
  "type": "Extension",
  "baseDefinition": "http://hl7.org/fhir/StructureDefinition/Extension",
  "derivation": "constraint",
  "differential": {
    "element": [
      {
        "id": "Extension",
        "path": "Extension",
        "short": "Vital Status",
        "definition": "Coded representation of a patient's vital status"
      },
      {
        "id": "Extension.extension",
        "path": "Extension.extension",
        "max": "0"
      },
      {
        "id": "Extension.url",
        "path": "Extension.url",
        "fixedUri": "https://rarelink.bih-charite.de/fhir/StructureDefinition/vital-status"
      },
      {
        "id": "Extension.value[x]",
        "path": "Extension.value[x]",
        "type": [
          {
            "code": "CodeableConcept"
          }
        ],
        "binding": {
          "strength": "extensible",
          "valueSet": "https://rarelink.bih-charite.de/fhir/ValueSet/vital-status-vs"
        }
      }
    ]
  }
}
