{
  "id": 671,
  "name": "florges",
  "types": [
    "fairy"
  ],
  "baseStats": {
    "hp": 78,
    "attack": 65,
    "defense": 68,
    "special_attack": 112,
    "special_defense": 154,
    "speed": 75
  },
  "height": 1.1,
  "weight": 10.0,
  "abilities": {
    "0": {
      "name": "flower-veil"
    },
    "H": {
      "name": "symbiosis"
    }
  },
  "moves": [
    "hyper-beam",
    "solar-beam",
    "petal-dance",
    "toxic",
    "psychic",
    "double-team",
    "light-screen",
    "metronome",
    "swift",
    "flash",
    "rest",
    "substitute",
    "snore",
    "protect",
    "giga-drain",
    "endure",
    "charm",
    "swagger",
    "attract",
    "sleep-talk",
    "heal-bell",
    "return",
    "frustration",
    "safeguard",
    "baton-pass",
    "synthesis",
    "hidden-power",
    "rain-dance",
    "sunny-day",
    "facade",
    "nature-power",
    "helping-hand",
    "trick",
    "wish",
    "magic-coat",
    "endeavor",
    "skill-swap",
    "secret-power",
    "aromatherapy",
    "covet",
    "magical-leaf",
    "calm-mind",
    "lucky-chant",
    "worry-seed",
    "seed-bomb",
    "energy-ball",
    "giga-impact",
    "defog",
    "grass-knot",
    "after-you",
    "round",
    "echoed-voice",
    "stored-power",
    "ally-switch",
    "petal-blizzard",
    "disarming-voice",
    "draining-kiss",
    "flower-shield",
    "grassy-terrain",
    "misty-terrain",
    "moonblast",
    "confide",
    "dazzling-gleam",
    "pollen-puff",
    "misty-explosion",
    "tera-blast",
    "trailblaze",
    "chilling-water",
    "alluring-voice",
    "psychic-noise"
  ],
  "generation": 6
}