{
  "id": 10171,
  "name": "moltres-galar",
  "types": [
    "dark",
    "flying"
  ],
  "baseStats": {
    "hp": 90,
    "attack": 85,
    "defense": 90,
    "special_attack": 100,
    "special_defense": 125,
    "speed": 90
  },
  "height": 2.0,
  "weight": 66.0,
  "abilities": {
    "0": {
      "name": "berserk"
    }
  },
  "moves": [
    "gust",
    "wing-attack",
    "fly",
    "take-down",
    "leer",
    "hyper-beam",
    "agility",
    "swift",
    "sky-attack",
    "rest",
    "substitute",
    "thief",
    "snore",
    "spite",
    "protect",
    "scary-face",
    "sandstorm",
    "endure",
    "steel-wing",
    "sleep-talk",
    "safeguard",
    "pain-split",
    "rain-dance",
    "sunny-day",
    "ancient-power",
    "shadow-ball",
    "memento",
    "facade",
    "taunt",
    "helping-hand",
    "imprison",
    "hyper-voice",
    "aerial-ace",
    "tailwind",
    "u-turn",
    "payback",
    "assurance",
    "sucker-punch",
    "dark-pulse",
    "air-slash",
    "brave-bird",
    "giga-impact",
    "nasty-plot",
    "foul-play",
    "after-you",
    "round",
    "hex",
    "acrobatics",
    "hurricane",
    "snarl",
    "lash-out",
    "dual-wingbeat",
    "fiery-wrath",
    "tera-blast"
  ],
  "generation": 9
}