{
  "id": 744,
  "name": "rockruff",
  "types": [
    "rock"
  ],
  "baseStats": {
    "hp": 45,
    "attack": 65,
    "defense": 40,
    "special_attack": 30,
    "special_defense": 40,
    "speed": 60
  },
  "height": 0.5,
  "weight": 9.2,
  "abilities": {
    "0": {
      "name": "keen-eye"
    },
    "1": {
      "name": "vital-spirit"
    },
    "H": {
      "name": "steadfast"
    }
  },
  "moves": [
    "swords-dance",
    "sand-attack",
    "tackle",
    "body-slam",
    "take-down",
    "thrash",
    "double-edge",
    "leer",
    "bite",
    "roar",
    "rock-throw",
    "dig",
    "toxic",
    "double-team",
    "rest",
    "rock-slide",
    "substitute",
    "snore",
    "protect",
    "scary-face",
    "mud-slap",
    "sandstorm",
    "endure",
    "charm",
    "swagger",
    "attract",
    "sleep-talk",
    "return",
    "frustration",
    "iron-tail",
    "hidden-power",
    "crunch",
    "facade",
    "taunt",
    "helping-hand",
    "endeavor",
    "hyper-voice",
    "crush-claw",
    "odor-sleuth",
    "rock-tomb",
    "iron-defense",
    "howl",
    "covet",
    "last-resort",
    "sucker-punch",
    "rock-polish",
    "earth-power",
    "thunder-fang",
    "fire-fang",
    "zen-headbutt",
    "rock-climb",
    "iron-head",
    "stone-edge",
    "stealth-rock",
    "round",
    "echoed-voice",
    "bulldoze",
    "snarl",
    "play-rough",
    "confide",
    "psychic-fangs",
    "stomping-tantrum",
    "tera-blast",
    "trailblaze"
  ],
  "generation": 7
}