{
  "id": 191,
  "name": "sunkern",
  "types": [
    "grass"
  ],
  "baseStats": {
    "hp": 30,
    "attack": 30,
    "defense": 30,
    "special_attack": 30,
    "special_defense": 30,
    "speed": 30
  },
  "height": 0.3,
  "weight": 1.8,
  "abilities": {
    "0": {
      "name": "chlorophyll"
    },
    "1": {
      "name": "solar-power"
    },
    "H": {
      "name": "early-bird"
    }
  },
  "moves": [
    "swords-dance",
    "cut",
    "tackle",
    "take-down",
    "double-edge",
    "absorb",
    "mega-drain",
    "leech-seed",
    "growth",
    "razor-leaf",
    "solar-beam",
    "toxic",
    "mimic",
    "double-team",
    "light-screen",
    "bide",
    "flash",
    "rest",
    "substitute",
    "snore",
    "curse",
    "protect",
    "sludge-bomb",
    "giga-drain",
    "endure",
    "swagger",
    "attract",
    "sleep-talk",
    "return",
    "frustration",
    "safeguard",
    "encore",
    "sweet-scent",
    "morning-sun",
    "synthesis",
    "hidden-power",
    "rain-dance",
    "sunny-day",
    "uproar",
    "facade",
    "nature-power",
    "helping-hand",
    "ingrain",
    "endeavor",
    "secret-power",
    "weather-ball",
    "grass-whistle",
    "bullet-seed",
    "magical-leaf",
    "natural-gift",
    "worry-seed",
    "seed-bomb",
    "energy-ball",
    "earth-power",
    "leaf-storm",
    "captivate",
    "grass-knot",
    "after-you",
    "round",
    "grassy-terrain",
    "confide",
    "tera-blast",
    "trailblaze"
  ],
  "generation": 2
}