{
  "id": 563,
  "name": "cofagrigus",
  "types": [
    "ghost"
  ],
  "baseStats": {
    "hp": 58,
    "attack": 50,
    "defense": 145,
    "special_attack": 95,
    "special_defense": 105,
    "speed": 30
  },
  "height": 1.7,
  "weight": 76.5,
  "abilities": {
    "0": {
      "name": "mummy"
    }
  },
  "moves": [
    "disable",
    "hyper-beam",
    "toxic",
    "psychic",
    "night-shade",
    "double-team",
    "haze",
    "dream-eater",
    "flash",
    "rest",
    "substitute",
    "thief",
    "snore",
    "curse",
    "spite",
    "protect",
    "scary-face",
    "destiny-bond",
    "endure",
    "swagger",
    "mean-look",
    "attract",
    "sleep-talk",
    "return",
    "frustration",
    "safeguard",
    "pain-split",
    "hidden-power",
    "rain-dance",
    "psych-up",
    "shadow-ball",
    "will-o-wisp",
    "facade",
    "trick",
    "role-play",
    "magic-coat",
    "revenge",
    "knock-off",
    "skill-swap",
    "imprison",
    "grudge",
    "snatch",
    "secret-power",
    "astonish",
    "fake-tears",
    "iron-defense",
    "block",
    "calm-mind",
    "shock-wave",
    "payback",
    "embargo",
    "power-swap",
    "guard-swap",
    "toxic-spikes",
    "dark-pulse",
    "energy-ball",
    "giga-impact",
    "nasty-plot",
    "shadow-claw",
    "zen-headbutt",
    "trick-room",
    "grass-knot",
    "ominous-wind",
    "guard-split",
    "power-split",
    "wonder-room",
    "telekinesis",
    "after-you",
    "round",
    "ally-switch",
    "hex",
    "phantom-force",
    "crafty-shield",
    "confide",
    "infestation",
    "body-press",
    "poltergeist"
  ],
  "generation": 5
}