{
  "id": 810,
  "name": "grookey",
  "types": [
    "grass"
  ],
  "baseStats": {
    "hp": 50,
    "attack": 65,
    "defense": 50,
    "special_attack": 40,
    "special_defense": 40,
    "speed": 65
  },
  "height": 0.3,
  "weight": 5.0,
  "abilities": {
    "0": {
      "name": "overgrow"
    },
    "H": {
      "name": "grassy-surge"
    }
  },
  "moves": [
    "mega-punch",
    "scratch",
    "swords-dance",
    "slam",
    "mega-kick",
    "body-slam",
    "take-down",
    "growl",
    "low-kick",
    "strength",
    "leech-seed",
    "growth",
    "razor-leaf",
    "solar-beam",
    "screech",
    "focus-energy",
    "swift",
    "rest",
    "substitute",
    "thief",
    "snore",
    "protect",
    "giga-drain",
    "endure",
    "false-swipe",
    "attract",
    "sleep-talk",
    "sunny-day",
    "fake-out",
    "uproar",
    "facade",
    "nature-power",
    "taunt",
    "knock-off",
    "endeavor",
    "bullet-seed",
    "magical-leaf",
    "hammer-arm",
    "u-turn",
    "assurance",
    "fling",
    "worry-seed",
    "seed-bomb",
    "drain-punch",
    "energy-ball",
    "leaf-storm",
    "grass-knot",
    "wood-hammer",
    "round",
    "acrobatics",
    "grass-pledge",
    "work-up",
    "grassy-terrain",
    "solar-blade",
    "branch-poke",
    "grassy-glide",
    "tera-blast",
    "trailblaze"
  ],
  "generation": 8
}