{
  "id": 510,
  "name": "liepard",
  "types": [
    "dark"
  ],
  "baseStats": {
    "hp": 64,
    "attack": 88,
    "defense": 50,
    "special_attack": 88,
    "special_defense": 50,
    "speed": 106
  },
  "height": 1.1,
  "weight": 37.5,
  "abilities": {
    "0": {
      "name": "limber"
    },
    "1": {
      "name": "unburden"
    },
    "H": {
      "name": "prankster"
    }
  },
  "moves": [
    "pay-day",
    "scratch",
    "cut",
    "sand-attack",
    "growl",
    "hyper-beam",
    "thunder-wave",
    "toxic",
    "screech",
    "double-team",
    "swift",
    "dream-eater",
    "fury-swipes",
    "rest",
    "slash",
    "substitute",
    "thief",
    "snore",
    "spite",
    "protect",
    "endure",
    "charm",
    "swagger",
    "attract",
    "sleep-talk",
    "return",
    "frustration",
    "baton-pass",
    "encore",
    "pursuit",
    "iron-tail",
    "hidden-power",
    "rain-dance",
    "sunny-day",
    "psych-up",
    "shadow-ball",
    "rock-smash",
    "fake-out",
    "torment",
    "facade",
    "taunt",
    "trick",
    "role-play",
    "assist",
    "knock-off",
    "snatch",
    "secret-power",
    "hyper-voice",
    "fake-tears",
    "aerial-ace",
    "covet",
    "u-turn",
    "payback",
    "assurance",
    "embargo",
    "sucker-punch",
    "dark-pulse",
    "night-slash",
    "seed-bomb",
    "giga-impact",
    "nasty-plot",
    "shadow-claw",
    "psycho-cut",
    "gunk-shot",
    "grass-knot",
    "hone-claws",
    "foul-play",
    "round",
    "echoed-voice",
    "snarl",
    "play-rough",
    "confide",
    "laser-focus",
    "throat-chop",
    "skitter-smack",
    "burning-jealousy",
    "lash-out"
  ],
  "generation": 5
}