{
  "id": 10066,
  "name": "sableye-mega",
  "types": [
    "dark",
    "ghost"
  ],
  "baseStats": {
    "hp": 50,
    "attack": 85,
    "defense": 125,
    "special_attack": 85,
    "special_defense": 115,
    "speed": 20
  },
  "height": 0.5,
  "weight": 161.0,
  "abilities": {
    "0": {
      "name": "magic-bounce"
    }
  },
  "moves": [
    "fire-punch",
    "ice-punch",
    "thunder-punch",
    "scratch",
    "cut",
    "leer",
    "low-kick",
    "dig",
    "toxic",
    "psychic",
    "night-shade",
    "double-team",
    "recover",
    "confuse-ray",
    "dream-eater",
    "flash",
    "fury-swipes",
    "rest",
    "substitute",
    "thief",
    "snore",
    "spite",
    "protect",
    "feint-attack",
    "foresight",
    "icy-wind",
    "detect",
    "swagger",
    "mean-look",
    "attract",
    "sleep-talk",
    "return",
    "frustration",
    "pain-split",
    "moonlight",
    "hidden-power",
    "rain-dance",
    "sunny-day",
    "psych-up",
    "shadow-ball",
    "rock-smash",
    "fake-out",
    "torment",
    "flatter",
    "will-o-wisp",
    "facade",
    "focus-punch",
    "taunt",
    "trick",
    "role-play",
    "magic-coat",
    "brick-break",
    "knock-off",
    "imprison",
    "snatch",
    "secret-power",
    "astonish",
    "rock-tomb",
    "signal-beam",
    "aerial-ace",
    "calm-mind",
    "shock-wave",
    "water-pulse",
    "gravity",
    "feint",
    "metal-burst",
    "payback",
    "embargo",
    "fling",
    "punishment",
    "sucker-punch",
    "poison-jab",
    "dark-pulse",
    "power-gem",
    "nasty-plot",
    "shadow-claw",
    "shadow-sneak",
    "zen-headbutt",
    "captivate",
    "hone-claws",
    "wonder-room",
    "telekinesis",
    "low-sweep",
    "foul-play",
    "round",
    "ally-switch",
    "incinerate",
    "quash",
    "retaliate",
    "snarl",
    "confide",
    "dazzling-gleam",
    "power-up-punch"
  ],
  "generation": 9
}