{
  "id": 100,
  "name": "voltorb",
  "types": [
    "electric"
  ],
  "baseStats": {
    "hp": 40,
    "attack": 30,
    "defense": 50,
    "special_attack": 55,
    "special_defense": 55,
    "speed": 100
  },
  "height": 0.5,
  "weight": 10.4,
  "abilities": {
    "0": {
      "name": "soundproof"
    },
    "1": {
      "name": "static"
    },
    "H": {
      "name": "aftermath"
    }
  },
  "moves": [
    "headbutt",
    "tackle",
    "take-down",
    "double-edge",
    "sonic-boom",
    "thunder-shock",
    "thunderbolt",
    "thunder-wave",
    "thunder",
    "toxic",
    "agility",
    "rage",
    "teleport",
    "mimic",
    "screech",
    "double-team",
    "light-screen",
    "reflect",
    "bide",
    "self-destruct",
    "swift",
    "flash",
    "explosion",
    "rest",
    "substitute",
    "thief",
    "snore",
    "curse",
    "protect",
    "zap-cannon",
    "endure",
    "rollout",
    "swagger",
    "spark",
    "sleep-talk",
    "return",
    "frustration",
    "hidden-power",
    "rain-dance",
    "mirror-coat",
    "torment",
    "facade",
    "charge",
    "taunt",
    "helping-hand",
    "magic-coat",
    "recycle",
    "secret-power",
    "metal-sound",
    "signal-beam",
    "shock-wave",
    "gyro-ball",
    "natural-gift",
    "sucker-punch",
    "magnet-rise",
    "discharge",
    "charge-beam",
    "electro-ball",
    "foul-play",
    "round",
    "volt-switch",
    "electroweb",
    "wild-charge",
    "confide",
    "eerie-impulse",
    "electric-terrain",
    "tera-blast"
  ],
  "generation": 1
}