{
  "id": 634,
  "name": "zweilous",
  "types": [
    "dark",
    "dragon"
  ],
  "baseStats": {
    "hp": 72,
    "attack": 85,
    "defense": 70,
    "special_attack": 65,
    "special_defense": 70,
    "speed": 58
  },
  "height": 1.4,
  "weight": 50.0,
  "abilities": {
    "0": {
      "name": "hustle"
    }
  },
  "moves": [
    "slam",
    "headbutt",
    "tackle",
    "body-slam",
    "take-down",
    "bite",
    "roar",
    "strength",
    "dragon-rage",
    "thunder-wave",
    "toxic",
    "screech",
    "double-team",
    "focus-energy",
    "rest",
    "substitute",
    "thief",
    "snore",
    "spite",
    "protect",
    "scary-face",
    "outrage",
    "endure",
    "swagger",
    "attract",
    "sleep-talk",
    "return",
    "frustration",
    "dragon-breath",
    "hidden-power",
    "rain-dance",
    "sunny-day",
    "crunch",
    "psych-up",
    "rock-smash",
    "beat-up",
    "uproar",
    "torment",
    "facade",
    "taunt",
    "helping-hand",
    "superpower",
    "secret-power",
    "hyper-voice",
    "shock-wave",
    "assurance",
    "dark-pulse",
    "aqua-tail",
    "dragon-pulse",
    "dragon-rush",
    "earth-power",
    "nasty-plot",
    "thunder-fang",
    "ice-fang",
    "fire-fang",
    "zen-headbutt",
    "draco-meteor",
    "double-hit",
    "round",
    "incinerate",
    "dragon-tail",
    "work-up",
    "snarl",
    "confide",
    "stomping-tantrum",
    "lash-out",
    "tera-blast",
    "dragon-cheer"
  ],
  "generation": 5
}